setup.cfg
setup.py
coro/__init__.py
coro/_coro.pyx
coro/backdoor.py
coro/event_queue.pyx
coro/frontdoor.py
coro/lru.pyx
coro/optional.py
coro/oserrors.pyx
coro/print_profile.py
coro/profiler.py
coro/read_stream.py
coro/signal_handler.py
coro/swap.c
coro/tb.py
coro.egg-info/PKG-INFO
coro.egg-info/SOURCES.txt
coro.egg-info/dependency_links.txt
coro.egg-info/requires.txt
coro.egg-info/top_level.txt
coro/asn1/__init__.py
coro/asn1/ber.pyx
coro/asn1/data_file.py
coro/asn1/python.pyx
coro/clocks/__init__.py
coro/clocks/tsc_time.pyx
coro/db/__init__.py
coro/db/postgres/__init__.py
coro/db/postgres/postgres.py
coro/db/postgres/proto.pyx
coro/dns/__init__.py
coro/dns/cache.py
coro/dns/exceptions.py
coro/dns/packet.pyx
coro/dns/reply.py
coro/dns/stub_resolver.py
coro/dns/surf.pyx
coro/emulation/__init__.py
coro/emulation/socket.py
coro/emulation/thread.py
coro/emulation/threading.py
coro/http/__init__.py
coro/http/client.py
coro/http/handlers.py
coro/http/http_date.py
coro/http/json_rpc.py
coro/http/protocol.py
coro/http/server.py
coro/http/session_handler.py
coro/http/spdy.py
coro/http/websocket.py
coro/http/zspdy.pyx
coro/ldap/query.pyx
coro/log/__init__.py
coro/log/asn1.py
coro/ssh/__init__.py
coro/ssh/auth/__init__.py
coro/ssh/auth/userauth.py
coro/ssh/cipher/__init__.py
coro/ssh/cipher/blowfish_cbc.py
coro/ssh/cipher/des3_cbc.py
coro/ssh/cipher/none.py
coro/ssh/compression/__init__.py
coro/ssh/compression/none.py
coro/ssh/connection/__init__.py
coro/ssh/connection/channel.py
coro/ssh/connection/connect.py
coro/ssh/connection/constants.py
coro/ssh/connection/data_buffer.py
coro/ssh/connection/interactive_session.py
coro/ssh/connection/tty_modes.py
coro/ssh/key_exchange/__init__.py
coro/ssh/key_exchange/diffie_hellman.py
coro/ssh/keys/__init__.py
coro/ssh/keys/dss.py
coro/ssh/keys/key_storage.py
coro/ssh/keys/openssh_authorized_keys.py
coro/ssh/keys/openssh_key_formats.py
coro/ssh/keys/openssh_key_storage.py
coro/ssh/keys/openssh_known_hosts.py
coro/ssh/keys/public_private_key.py
coro/ssh/keys/rebuild.py
coro/ssh/keys/remote_host.py
coro/ssh/keys/rsa.py
coro/ssh/keys/static_key_storage.py
