Metadata-Version: 1.1
Name: coro
Version: 1.0.3-000
Summary: IronPort Coroutine/Threading Library
Home-page: http://github.com/ironport/shrapnel
Author: Sam Rushing, Eric Huss, IronPort Engineering
Author-email: sam-coro@rushing.nightmare.com
License: MIT
Download-URL: http://github.com/ironport/shrapnel/tarball/master#egg=coro-1.0.2
Platform: UNKNOWN
